game_of_life_uc/__init__.py
game_of_life_uc/__main__.py
game_of_life_uc/game_code.py
game_of_life_uc-0.1.2.dist-info/METADATA
game_of_life_uc-0.1.2.dist-info/WHEEL
game_of_life_uc-0.1.2.dist-info/entry_points.txt
game_of_life_uc-0.1.2.dist-info/RECORD
