Metadata-Version: 2.1
Name: game-of-life-uc
Version: 0.1.2
Summary: 
Author: Pedro Juan Royo
Author-email: pedro.juan.royo@gmail.com
Requires-Python: >=3.11,<4.0
Classifier: Programming Language :: Python :: 3
Classifier: Programming Language :: Python :: 3.11
